{"0":{"Date":"2020-07-09","Origin":"SIN","Destination":"LON","Price":"$391","Departure Time":"11:00","Arrival Time":"8:20","Flight duration":"28h 20m","URL":"https:\/\/www.kayak.com\/book\/flight?code=GHHiJvI5GN.6We7wBYoN-cNUvH8T-y68A.39058.8524bc8efda56d750425466b3829d2dd&h=18199532f942&sub=E-139119fa0bd"},"1":{"Date":"2020-07-10","Origin":"SIN","Destination":"LON","Price":"$315","Departure Time":"11:55","Arrival Time":"9:05","Flight duration":"16h 10m","URL":"https:\/\/www.kayak.com\/book\/flight?code=GHHiNHekLu.-COZ-Slz34a7ImCnqdurig.31427.8bfa2564bf48b60e7e6dcb543ea1ad36&h=4c4dbd217960&sub=E-1e920e1ecb2"},"2":{"Date":"2020-07-11","Origin":"SIN","Destination":"LON","Price":"$368","Departure Time":"9:20","Arrival Time":"8:20","Flight duration":"30h 00m","URL":"https:\/\/www.kayak.com\/book\/flight?code=GHFiHnSxpk.6We7wBYoN-cNUvH8T-y68A.36776.f3cae2f26b07d046a0a0190ee3f7242e&h=15c4fd3e52eb&sub=E-139119fa0bd"},"3":{"Date":"2020-07-12","Origin":"SIN","Destination":"LON","Price":"$315","Departure Time":"11:55","Arrival Time":"9:05","Flight duration":"16h 10m","URL":"https:\/\/www.kayak.com\/book\/flight?code=GHECMEO4pr.-COZ-Slz34a7ImCnqdurig.31427.d3f5ff6940709405fc209135d3551218&h=30701a1f7f21&sub=E-1e920e1ecb2"},"4":{"Date":"2020-07-13","Origin":"SIN","Destination":"LON","Price":"$401","Departure Time":"6:20","Arrival Time":"6:20","Flight duration":"19h 00m","URL":"https:\/\/www.kayak.com\/book\/flight?code=GHHCKRVDSS.-COZ-Slz34a7ImCnqdurig.40003.5420563f0ae0f0de814fcacf35cac8c0&h=f5c264192ba7&sub=E-1e920e1ecb2"},"5":{"Date":"2020-07-14","Origin":"SIN","Destination":"LON","Price":"$435","Departure Time":"8:00","Arrival Time":"6:45","Flight duration":"17h 45m","URL":"https:\/\/www.kayak.com\/book\/flight?code=GHGiFMwmxc.GVLrpdPpgeA.43411.fb1dad71d0f157dd3215104512efecfd&h=1cd1e361f458&sub=E-1b9d95b7805"},"6":{"Date":"2020-07-15","Origin":"SIN","Destination":"LON","Price":"$401","Departure Time":"6:20","Arrival Time":"6:20","Flight duration":"19h 00m","URL":"https:\/\/www.kayak.com\/book\/flight?code=GHFCQvhvsC.-COZ-Slz34a7ImCnqdurig.40003.17186ad39a153641bc4ec073b4820f69&h=d37b7e8d2388&sub=E-1e920e1ecb2"},"7":{"Date":"2020-07-16","Origin":"SIN","Destination":"LON","Price":"$435","Departure Time":"8:00","Arrival Time":"6:45","Flight duration":"17h 45m","URL":"https:\/\/www.kayak.com\/book\/flight?code=GHHCPYPfs9.GVLrpdPpgeA.43411.b5305f6213715bde2dfdb2814cd86740&h=fd0468672f8b&sub=E-1b9d95b7805"},"8":{"Date":"2020-07-17","Origin":"SIN","Destination":"LON","Price":"$315","Departure Time":"11:55","Arrival Time":"9:05","Flight duration":"16h 10m","URL":"https:\/\/www.kayak.com\/book\/flight?code=GHEiPNEAaC.-COZ-Slz34a7ImCnqdurig.31427.3e2580e37e03f888bf2001e61d7c2cca&h=43a7cc46d01d&sub=E-1e920e1ecb2"},"9":{"Date":"2020-07-18","Origin":"SIN","Destination":"LON","Price":"$387","Departure Time":"9:20","Arrival Time":"8:20","Flight duration":"30h 00m","URL":"https:\/\/www.kayak.com\/book\/flight?code=GHGiHB9yF_.6We7wBYoN-cNUvH8T-y68A.38645.2c9dd6ff1a8a8387f773cdc2bd19a58a&h=d5f4a42c58f1&sub=E-139119fa0bd"},"10":{"Date":"2020-07-19","Origin":"SIN","Destination":"LON","Price":"$427","Departure Time":"6:20","Arrival Time":"6:20","Flight duration":"19h 00m","URL":"https:\/\/www.kayak.com\/book\/flight?code=GHEiOUJuOZ.-COZ-Slz34a7ImCnqdurig.42676.8f5ff14aa09f2b042825a040ef5cda38&h=1720a29723b5&sub=E-1e920e1ecb2"},"11":{"Date":"2020-07-20","Origin":"SIN","Destination":"LON","Price":"$401","Departure Time":"6:20","Arrival Time":"6:20","Flight duration":"19h 00m","URL":"https:\/\/www.kayak.com\/book\/flight?code=GHEiTvSp3G.-COZ-Slz34a7ImCnqdurig.40003.9fd05cfae0daa1fda78841c5a25764dc&h=9632a65ad1a7&sub=E-1e920e1ecb2"},"12":{"Date":"2020-07-21","Origin":"SIN","Destination":"LON","Price":"$316","Departure Time":"11:55","Arrival Time":"9:25","Flight duration":"16h 30m","URL":"https:\/\/www.kayak.com\/book\/flight?code=GHEiR3dFAC.6We7wBYoN-cNUvH8T-y68A.31586.3993959032ac6f2a70f79105b2f713ec&h=b7d5dfd76fe7&sub=E-139119fa0bd"},"13":{"Date":"2020-07-22","Origin":"SIN","Destination":"LON","Price":"$532","Departure Time":"11:30","Arrival Time":"8:10","Flight duration":"15h 40m","URL":"https:\/\/www.kayak.com\/book\/flight?code=GHGiOrSB5X.k__A2aLI5Kc.53140.8c94f2fd76bb856e9a7afc191a593259&h=361f23630296&sub=E-1056e4f4f1c"}}