{"0":{"Date":"2020-08-17","Origin":"SIN","Destination":"HKG","Price":"$140","Departure Time":"5:45","Arrival Time":"9:25","Flight duration":"3h 40m","URL":"https:\/\/www.kayak.com\/book\/flight?code=GEHCLrCOjK.3trpTcyJlBVFj024N3_sTg.13982.96d58c751b104496cf747bb775cb5f2b&h=fc24ec39d089&sub=E-1c51e2eae46"},"1":{"Date":"2020-08-18","Origin":"SIN","Destination":"HKG","Price":"$127","Departure Time":"2:15","Arrival Time":"6:20","Flight duration":"4h 05m","URL":"https:\/\/www.kayak.com\/book\/flight?code=GFFCAJtE82.6We7wBYoN-cNUvH8T-y68A.12662.ed0a5428f1e70584c8ceb02697c83280&h=7dae7534d7cb&sub=E-139119fa0bd"},"2":{"Date":"2020-08-19","Origin":"SIN","Destination":"HKG","Price":"$140","Departure Time":"5:45","Arrival Time":"9:25","Flight duration":"3h 40m","URL":"https:\/\/www.kayak.com\/book\/flight?code=GFHiKVVzUt.3trpTcyJlBVFj024N3_sTg.13982.913a5b969927c4f3cb45df32cf6ff6ce&h=70b615ced8fc&sub=E-1c51e2eae46"},"3":{"Date":"2020-08-20","Origin":"SIN","Destination":"HKG","Price":"$184","Departure Time":"6:00","Arrival Time":"10:05","Flight duration":"4h 05m","URL":"https:\/\/www.kayak.com\/book\/flight?code=GFFCBDN60W.lYaNfPGU4HvBDARZyLA7ng.18382.e2b040c1a418e8d7d688c6b871d29391&h=63927113e788&sub=E-11393bdb484"},"4":{"Date":"2020-08-21","Origin":"SIN","Destination":"HKG","Price":"$127","Departure Time":"2:15","Arrival Time":"6:20","Flight duration":"4h 05m","URL":"https:\/\/www.kayak.com\/book\/flight?code=GFGiN-ckjv.6We7wBYoN-cNUvH8T-y68A.12662.2e291822d939f2e4480d0d6ed0ef26e4&h=aae9e5c02871&sub=E-139119fa0bd"},"5":{"Date":"2020-08-22","Origin":"SIN","Destination":"HKG","Price":"$140","Departure Time":"5:45","Arrival Time":"9:25","Flight duration":"3h 40m","URL":"https:\/\/www.kayak.com\/book\/flight?code=GFEiNQ2ctZ.3trpTcyJlBVFj024N3_sTg.13982.296c727605c4248a3b1e36093199259e&h=b092b351b798&sub=E-1c51e2eae46"},"6":{"Date":"2020-08-23","Origin":"SIN","Destination":"HKG","Price":"$127","Departure Time":"2:15","Arrival Time":"6:20","Flight duration":"4h 05m","URL":"https:\/\/www.kayak.com\/book\/flight?code=GFGCP-as2q.6We7wBYoN-cNUvH8T-y68A.12662.88c9261642daef07e65af0f69bde45a2&h=94ef4f14bacb&sub=E-139119fa0bd"},"7":{"Date":"2020-08-24","Origin":"SIN","Destination":"HKG","Price":"$140","Departure Time":"5:45","Arrival Time":"9:25","Flight duration":"3h 40m","URL":"https:\/\/www.kayak.com\/book\/flight?code=GFGCEmgPe4.3trpTcyJlBVFj024N3_sTg.13982.482308e402175e6783907ced228c321e&h=8a2b7edb2f26&sub=E-1c51e2eae46"},"8":{"Date":"2020-08-25","Origin":"SIN","Destination":"HKG","Price":"$127","Departure Time":"2:15","Arrival Time":"6:20","Flight duration":"4h 05m","URL":"https:\/\/www.kayak.com\/book\/flight?code=GFFiRs7TZU.6We7wBYoN-cNUvH8T-y68A.12662.5c64f7d29510b8337475b31c6b0a94e4&h=a2011ad8b669&sub=E-139119fa0bd"},"9":{"Date":"2020-08-26","Origin":"SIN","Destination":"HKG","Price":"$140","Departure Time":"5:45","Arrival Time":"9:25","Flight duration":"3h 40m","URL":"https:\/\/www.kayak.com\/book\/flight?code=GFFiPSR2lM.3trpTcyJlBVFj024N3_sTg.13982.6380727fe231e93fb587a8ec63871e9d&h=3340fd7e0632&sub=E-1c51e2eae46"},"10":{"Date":"2020-08-27","Origin":"SIN","Destination":"HKG","Price":"$184","Departure Time":"6:00","Arrival Time":"10:05","Flight duration":"4h 05m","URL":"https:\/\/www.kayak.com\/book\/flight?code=GFFCCALDec.lYaNfPGU4HvBDARZyLA7ng.18382.e62790dfea590b7fcb99a4585dccdf1f&h=49efc7d6fd10&sub=E-11393bdb484"},"11":{"Date":"2020-08-28","Origin":"SIN","Destination":"HKG","Price":"$133","Departure Time":"2:15","Arrival Time":"6:20","Flight duration":"4h 05m","URL":"https:\/\/www.kayak.com\/book\/flight?code=GFFCNBNwxH.6Ky586fB8Xouqge7lldQQw.13273.6e86f04764740a616f7ac3416d3321dc&h=a518909191b1&sub=E-1f08093e2f1"},"12":{"Date":"2020-08-29","Origin":"SIN","Destination":"HKG","Price":"$140","Departure Time":"5:45","Arrival Time":"9:25","Flight duration":"3h 40m","URL":"https:\/\/www.kayak.com\/book\/flight?code=GFFCC7IQT3.3trpTcyJlBVFj024N3_sTg.13982.9bb441998703d2927100fa43a8980f6c&h=672010811774&sub=E-1c51e2eae46"},"13":{"Date":"2020-08-30","Origin":"SIN","Destination":"HKG","Price":"$127","Departure Time":"2:15","Arrival Time":"6:20","Flight duration":"4h 05m","URL":"https:\/\/www.kayak.com\/book\/flight?code=GFEiIKZUpc.6We7wBYoN-cNUvH8T-y68A.12662.63c1957bd8a6a9f52460c0c0aca1dba9&h=0894f4c3c8aa&sub=E-139119fa0bd"}}